xml_validators/__init__.py
xml_validators/validators.py
xml_validators-1.0.1.dist-info/METADATA
xml_validators-1.0.1.dist-info/WHEEL
xml_validators-1.0.1.dist-info/top_level.txt
xml_validators-1.0.1.dist-info/RECORD
