Metadata-Version: 2.1
Name: xml-validators
Version: 1.0.1
Summary: For XML Preprocessing
Home-page: https://github.com/Wonseok-An/xml_validators
Author: Wonseok An
Author-email: wonseok.an95@gmail.com
License: MIT
Platform: UNKNOWN
Requires-Python: >=3
